entari_plugin_server-0.5.1.dist-info/METADATA
entari_plugin_server-0.5.1.dist-info/WHEEL
entari_plugin_server-0.5.1.dist-info/entry_points.txt
entari_plugin_server-0.5.1.dist-info/licenses/LICENSE
entari_plugin_server/README.md
entari_plugin_server/__init__.py
entari_plugin_server/_adapter.py
entari_plugin_server/config.py
entari_plugin_server/patch.py
entari_plugin_server-0.5.1.dist-info/RECORD
