Metadata-Version: 2.1
Name: entari-plugin-server
Version: 0.5.1
Summary: Entari plugin for running Satori Server
Author-Email: RF-Tar-Railt <rf_tar_railt@qq.com>
License: MIT
Project-URL: homepage, https://github.com/ArcletProject/entari-plugin-server
Project-URL: repository, https://github.com/ArcletProject/entari-plugin-server
Requires-Python: >=3.10
Requires-Dist: arclet-entari<0.17.0,>=0.16.5
Requires-Dist: satori-python-server<0.18.0,>=0.17.2
Provides-Extra: fastapi
Requires-Dist: fastapi>=0.116.1; extra == "fastapi"
